cbs_sports_api/__init__.py
cbs_sports_api/_version.py
cbs_sports_api/bracket.py
cbs_sports_api/cbs_requests.py
cbs_sports_api/entry.py
cbs_sports_api/matchup.py
cbs_sports_api/pool.py
cbs_sports_api/team.py
cbs_sports_api-0.1.0.dist-info/METADATA
cbs_sports_api-0.1.0.dist-info/WHEEL
cbs_sports_api-0.1.0.dist-info/licenses/LICENSE
cbs_sports_api-0.1.0.dist-info/RECORD
