Metadata-Version: 2.4
Name: cbs-sports-api
Version: 0.1.0
Summary: A package to extract CBS Sports fantasy league data.
Project-URL: Homepage, https://github.com/JohnDiebold/cbs-sports-api
Project-URL: Issues, https://github.com/JohnDiebold/cbs-sports-api/issues
Author-email: John Diebold <cbs.sports.api@gmail.com>
License-Expression: MIT
License-File: LICENSE
Classifier: Operating System :: OS Independent
Classifier: Programming Language :: Python :: 3
Requires-Python: >=3.8
Requires-Dist: requests
